datamaker/__init__.py
datamaker/client/__init__.py
datamaker/client/exceptions.py
datamaker/client/utils.py
datamaker/client/mixins/__init__.py
datamaker/client/mixins/annotation.py
datamaker/client/mixins/dataset.py
datamaker/client/mixins/hitl.py
datamaker/client/mixins/integration.py
datamaker/client/mixins/ml.py
datamaker/plugins/__init__.py
datamaker/plugins/exports.py
datamaker/plugins/imports.py
datamaker/plugins/neural_networks.py
datamaker/plugins/preprocessors.py
datamaker/utils/__init__.py
datamaker/utils/file.py
datamaker/utils/logger.py
datamaker/utils/string.py
datamaker_sdk-0.9.dist-info/LICENSE
datamaker_sdk-0.9.dist-info/METADATA
datamaker_sdk-0.9.dist-info/WHEEL
datamaker_sdk-0.9.dist-info/top_level.txt
datamaker_sdk-0.9.dist-info/RECORD
