Metadata-Version: 2.1
Name: datamaker-sdk
Version: 0.9
Summary: datamaker sdk
Home-page: https://www.datamaker.io
Author: datamaker
Author-email: developer@datamaker.io
License: MIT
Classifier: Programming Language :: Python :: 3
Classifier: License :: OSI Approved :: MIT License
Classifier: Operating System :: OS Independent
Classifier: Programming Language :: Python
Classifier: Programming Language :: Python :: 3.6
Classifier: Programming Language :: Python :: 3.7
Classifier: Programming Language :: Python :: 3.8
Classifier: Programming Language :: Python :: 3.9
Classifier: Programming Language :: Python :: Implementation :: CPython
Classifier: Programming Language :: Python :: Implementation :: PyPy
Classifier: Topic :: Software Development :: Libraries :: Python Modules
Requires-Python: >=3.6
License-File: LICENSE
Requires-Dist: django >=4.0.4
Requires-Dist: djangorestframework >=3.13.1
Requires-Dist: django-constance[database] >=2.8.0
Requires-Dist: requests >=2.26.0
Requires-Dist: tqdm >=4.62.3
